CHANGELOG.txt
LICENSE.txt
MANIFEST.in
README.txt
setup.py
arsibasiccalculator/__init__.py
arsibasiccalculator.egg-info/PKG-INFO
arsibasiccalculator.egg-info/SOURCES.txt
arsibasiccalculator.egg-info/dependency_links.txt
arsibasiccalculator.egg-info/top_level.txt
lib/python3.9/site-packages/_distutils_hack/__init__.py
lib/python3.9/site-packages/_distutils_hack/override.py
lib/python3.9/site-packages/pip/__init__.py
lib/python3.9/site-packages/pip/__main__.py
lib/python3.9/site-packages/pip-21.0.1.dist-info/LICENSE.txt
lib/python3.9/site-packages/pip-21.0.1.dist-info/entry_points.txt
lib/python3.9/site-packages/pip-21.0.1.dist-info/top_level.txt
lib/python3.9/site-packages/pip/_internal/__init__.py
lib/python3.9/site-packages/pip/_internal/build_env.py
lib/python3.9/site-packages/pip/_internal/cache.py
lib/python3.9/site-packages/pip/_internal/configuration.py
lib/python3.9/site-packages/pip/_internal/exceptions.py
lib/python3.9/site-packages/pip/_internal/locations.py
lib/python3.9/site-packages/pip/_internal/main.py
lib/python3.9/site-packages/pip/_internal/pyproject.py
lib/python3.9/site-packages/pip/_internal/self_outdated_check.py
lib/python3.9/site-packages/pip/_internal/wheel_builder.py
lib/python3.9/site-packages/pip/_internal/cli/__init__.py
lib/python3.9/site-packages/pip/_internal/cli/autocompletion.py
lib/python3.9/site-packages/pip/_internal/cli/base_command.py
lib/python3.9/site-packages/pip/_internal/cli/cmdoptions.py
lib/python3.9/site-packages/pip/_internal/cli/command_context.py
lib/python3.9/site-packages/pip/_internal/cli/main.py
lib/python3.9/site-packages/pip/_internal/cli/main_parser.py
lib/python3.9/site-packages/pip/_internal/cli/parser.py
lib/python3.9/site-packages/pip/_internal/cli/progress_bars.py
lib/python3.9/site-packages/pip/_internal/cli/req_command.py
lib/python3.9/site-packages/pip/_internal/cli/spinners.py
lib/python3.9/site-packages/pip/_internal/cli/status_codes.py
lib/python3.9/site-packages/pip/_internal/commands/__init__.py
lib/python3.9/site-packages/pip/_internal/commands/cache.py
lib/python3.9/site-packages/pip/_internal/commands/check.py
lib/python3.9/site-packages/pip/_internal/commands/completion.py
lib/python3.9/site-packages/pip/_internal/commands/configuration.py
lib/python3.9/site-packages/pip/_internal/commands/debug.py
lib/python3.9/site-packages/setuptools-54.1.1.dist-info/dependency_links.txt
lib/python3.9/site-packages/setuptools-54.1.1.dist-info/entry_points.txt
lib/python3.9/site-packages/setuptools-54.1.1.dist-info/top_level.txt
